clisops/__init__.py
clisops/__version__.py
clisops/config.py
clisops/exceptions.py
clisops/project_utils.py
clisops/core/__init__.py
clisops/core/average.py
clisops/core/regrid.py
clisops/core/subset.py
clisops/etc/roocs.ini
clisops/ops/__init__.py
clisops/ops/average.py
clisops/ops/base_operation.py
clisops/ops/regrid.py
clisops/ops/subset.py
clisops/parameter/__init__.py
clisops/parameter/_utils.py
clisops/parameter/area_parameter.py
clisops/parameter/base_parameter.py
clisops/parameter/collection_parameter.py
clisops/parameter/dimension_parameter.py
clisops/parameter/level_parameter.py
clisops/parameter/parameterise.py
clisops/parameter/time_components_parameter.py
clisops/parameter/time_parameter.py
clisops/utils/__init__.py
clisops/utils/common.py
clisops/utils/dataset_utils.py
clisops/utils/file_namers.py
clisops/utils/file_utils.py
clisops/utils/mini-esgf-data_registry.txt
clisops/utils/output_utils.py
clisops/utils/testing.py
clisops/utils/time_utils.py
clisops/utils/xclim-testdata_registry.txt
clisops-0.17.0.dist-info/licenses/LICENSE
clisops-0.17.0.dist-info/WHEEL
clisops-0.17.0.dist-info/METADATA
clisops-0.17.0.dist-info/RECORD
