Metadata-Version: 2.4
Name: clisops
Version: 0.17.0
Summary: CLISOPS - Climate simulation operations.
Keywords: clisops,xarray,climate,gis,subsetting,operations
Author-email: Elle Smith <eleanor.smith@stfc.ac.uk>, Ag Stephens <ag.stephens@stfc.ac.uk>, Carsten Ehbrecht <ehbrecht@dkrz.de>, Trevor James Smith <smith.trevorj@ouranos.ca>
Maintainer-email: Carsten Ehbrecht <ehbrecht@dkrz.de>, Trevor James Smith <smith.trevorj@ouranos.ca>
Requires-Python: >=3.11.0
Classifier: Development Status :: 5 - Production/Stable
Classifier: Intended Audience :: Developers
Classifier: Intended Audience :: System Administrators
Classifier: Intended Audience :: Science/Research
Classifier: License :: OSI Approved :: BSD License
Classifier: Natural Language :: English
Classifier: Operating System :: OS Independent
Classifier: Programming Language :: Python
Classifier: Programming Language :: Python :: 3
Classifier: Programming Language :: Python :: 3 :: Only
Classifier: Programming Language :: Python :: 3.11
Classifier: Programming Language :: Python :: 3.12
Classifier: Programming Language :: Python :: 3.13
Classifier: Topic :: Scientific/Engineering
Classifier: Topic :: Scientific/Engineering :: Atmospheric Science
Classifier: Topic :: Scientific/Engineering :: GIS
Classifier: Topic :: Scientific/Engineering :: Information Analysis
Classifier: Topic :: Software Development :: Libraries :: Python Modules
Classifier: Topic :: System :: Distributed Computing
Classifier: Typing :: Typed
License-File: LICENSE
Requires-Dist: aiohttp
Requires-Dist: bottleneck >=1.3.1
Requires-Dist: cartopy >=0.23
Requires-Dist: cf-xarray >=0.10.6
Requires-Dist: cftime >=1.4.1
Requires-Dist: dask[complete] >=2023.6.0
Requires-Dist: fastparquet >=2024.11.0
Requires-Dist: filelock >=3.15.4
Requires-Dist: fsspec >=2023.9.0
Requires-Dist: geopandas >=1.0
Requires-Dist: jinja2 >=2.11
Requires-Dist: loguru >=0.5.3
Requires-Dist: numpy >=1.26.0,<2.3.0
Requires-Dist: packaging >=23.2
Requires-Dist: pandas >=2.2.0
Requires-Dist: platformdirs >=4.0
Requires-Dist: pooch >=1.8.0
Requires-Dist: pyproj >=3.3.0
Requires-Dist: requests
Requires-Dist: roocs_grids >=0.1.2
Requires-Dist: s3fs >=2025.5.1
Requires-Dist: scipy>=1.11.0
Requires-Dist: shapely >=2.0
Requires-Dist: xarray >=2025.1.1,<2025.11.0
Requires-Dist: zarr >=2.13.0,<3.0
Requires-Dist: bump-my-version >=1.2.0 ; extra == "dev"
Requires-Dist: coverage[toml] >=7.5.0 ; extra == "dev"
Requires-Dist: deptry >=0.23.1 ; extra == "dev"
Requires-Dist: flake8 >=7.3.0 ; extra == "dev"
Requires-Dist: flake8-rst-docstrings >=0.4.0 ; extra == "dev"
Requires-Dist: h5netcdf >=1.5.0 ; extra == "dev"
Requires-Dist: pip >=25.2 ; extra == "dev"
Requires-Dist: pre-commit >=3.5.0 ; extra == "dev"
Requires-Dist: pytest >=8.0.0 ; extra == "dev"
Requires-Dist: pytest-cov >=5.0.0 ; extra == "dev"
Requires-Dist: pytest-loguru >=0.3.0 ; extra == "dev"
Requires-Dist: pytest-xdist[psutil] >=3.2 ; extra == "dev"
Requires-Dist: ruff >=0.14.3 ; extra == "dev"
Requires-Dist: tox >=4.30.3 ; extra == "dev"
Requires-Dist: watchdog >=4.0.0 ; extra == "dev"
Requires-Dist: ipykernel ; extra == "docs"
Requires-Dist: ipython >=8.5.0 ; extra == "docs"
Requires-Dist: ipython_genutils ; extra == "docs"
Requires-Dist: jupyter_client ; extra == "docs"
Requires-Dist: matplotlib >=3.6.0 ; extra == "docs"
Requires-Dist: nbconvert >=7.14.0 ; extra == "docs"
Requires-Dist: nbsphinx >=0.9.5 ; extra == "docs"
Requires-Dist: sphinx >=7.1.0,<8.2 ; extra == "docs"
Requires-Dist: sphinx-autodoc-typehints ; extra == "docs"
Requires-Dist: sphinx-codeautolink ; extra == "docs"
Requires-Dist: sphinx-copybutton ; extra == "docs"
Requires-Dist: sphinx-rtd-theme >=1.0 ; extra == "docs"
Requires-Dist: xesmf >=0.9.2 ; extra == "extras"
Requires-Dist: xarray >=2025.6.0 ; extra == "extras"
Project-URL: About ROOCS, https://roocs.github.io/
Project-URL: Changelog, https://clisops.readthedocs.io/en/latest/history.html
Project-URL: Homepage, https://clisops.readthedocs.io/
Project-URL: Issue tracker, https://github.com/roocs/clisops/issues
Project-URL: Source, https://github.com/roocs/clisops/
Provides-Extra: dev
Provides-Extra: docs
Provides-Extra: extras
